htrc_text_processing/__init__.py
htrc_text_processing/htrc/__init__.py
htrc_text_processing/htrc/models.py
htrc_text_processing/htrc/runningheaders.py
htrc_text_processing/htrc/tests.py
htrc_text_processing/htrc/utils.py
htrc_text_processing-0.0.2.dist-info/LICENSE
htrc_text_processing-0.0.2.dist-info/METADATA
htrc_text_processing-0.0.2.dist-info/WHEEL
htrc_text_processing-0.0.2.dist-info/top_level.txt
htrc_text_processing-0.0.2.dist-info/RECORD
