Metadata-Version: 2.1
Name: htrc-text-processing
Version: 0.0.2
Summary: Text processing and analysis for HathiTrust Research Center
Home-page: https://github.com/ashan8k/htrc-text-processing
Author: Ashan Liyanage, Ryan Dubnicek
Author-email: ashan8k@gmail.com
License: UNKNOWN
Platform: UNKNOWN
Classifier: Programming Language :: Python :: 3
Classifier: License :: OSI Approved :: University of Illinois/NCSA Open Source License
Classifier: Operating System :: OS Independent
Requires-Python: >=3.6
